vr/__init__.py
vr/imager/__init__.py
vr/imager/__main__.py
vr/imager/build.py
vr/imager/command.py
vr/imager/templates/base_image.lxc
vr.imager-2.0.1.dist-info/LICENSE
vr.imager-2.0.1.dist-info/METADATA
vr.imager-2.0.1.dist-info/WHEEL
vr.imager-2.0.1.dist-info/entry_points.txt
vr.imager-2.0.1.dist-info/top_level.txt
vr.imager-2.0.1.dist-info/RECORD
